HUANYUAN/__init__.py
HUANYUAN/huanyuan.py
huanyuan-3.0.2.dist-info/LICENSE
huanyuan-3.0.2.dist-info/METADATA
huanyuan-3.0.2.dist-info/WHEEL
huanyuan-3.0.2.dist-info/entry_points.txt
huanyuan-3.0.2.dist-info/top_level.txt
huanyuan-3.0.2.dist-info/zip-safe
huanyuan-3.0.2.dist-info/RECORD
