Metadata-Version: 2.1
Name: huanyuan
Version: 3.0.2
Summary: Fast switching PyPi mirror image source
Home-page: https://gitee.com/qsbye/python-huanyuan
Author: Original:HangfengYang,Edited by qsbye
Author-email: yhf5fhy@gmail.com,2557877116@qq.com
License: MIT
Keywords: python、PyPi source、terminal
License-File: LICENSE
Requires-Dist: docopt
